LICENSE
monarchmoney_typed/__init__.py
monarchmoney_typed/icon.py
monarchmoney_typed/models.py
monarchmoney_typed/monarchmoney_typed.py
monarchmoney_typed/py.typed
monarchmoney_typed-0.1.5.dist-info/LICENSE
monarchmoney_typed-0.1.5.dist-info/METADATA
monarchmoney_typed-0.1.5.dist-info/WHEEL
monarchmoney_typed-0.1.5.dist-info/RECORD
