Metadata-Version: 2.1
Name: monarchmoney_typed
Version: 0.1.5
Summary: A Typed wrapper around Monarch Money
Author: Jeff Stein
Author-email: jeffstein@gmail.com
Requires-Python: >=3.12,<4.0
Classifier: Programming Language :: Python :: 3
Classifier: Programming Language :: Python :: 3.12
Requires-Dist: monarchmoney (>=0.1.13,<0.2.0)
